dbpal/__init__.py
dbpal/config.py
dbpal/data.py
dbpal/tables.py
dbpal/utils.py
dbpal/tests/conftest.py
dbpal/tests/helpers.py
dbpal/tests/test_data.py
dbpal/tests/test_utils.py
dbpal/tests/example_files/data.jsonl
dbpal/tests/example_files/data.parquet
dbpal-0.0.3.dist-info/LICENSE
dbpal-0.0.3.dist-info/METADATA
dbpal-0.0.3.dist-info/WHEEL
dbpal-0.0.3.dist-info/top_level.txt
dbpal-0.0.3.dist-info/RECORD
